{
    "keep": {
        "days": true,
        "amount": 14
    },
    "auditLog": "H:\\All project\\Programming Hero\\Next-Level-Practise-1\\logs\\winston\\success\\.6ebae24bc0a50653d047f1c2e166b0e9a0c42f3d-audit.json",
    "files": [
        {
            "date": 1685774919660,
            "name": "H:\\All project\\Programming Hero\\Next-Level-Practise-1\\logs\\winston\\success\\UMS-2023-06-03-12.log",
            "hash": "7891826a01c1cc76d92a3b2f54c4cc40323b25e4555bfb59a677b448824d39c8"
        },
        {
            "date": 1685775903538,
            "name": "H:\\All project\\Programming Hero\\Next-Level-Practise-1\\logs\\winston\\success\\UMS-2023-06-03-13.log",
            "hash": "f6b0304018980d077622cac3469a38816ee843eac6cb542806bb63d40d5385ec"
        },
        {
            "date": 1685880094559,
            "name": "H:\\All project\\Programming Hero\\Next-Level-Practise-1\\logs\\winston\\success\\UMS-2023-06-04-18.log",
            "hash": "3f6258df846a6da78c9727d126321ad2daa093fd28f63f36ff9a2cafa23af244"
        },
        {
            "date": 1686209664446,
            "name": "H:\\All project\\Programming Hero\\Next-Level-Practise-1\\logs\\winston\\success\\UMS-2023-06-08-13.log",
            "hash": "c6c48f996d7be8853907fe6b5f934ca6c63f0f4a6dffca3b1ae07820509ce6b9"
        },
        {
            "date": 1686291045635,
            "name": "H:\\All project\\Programming Hero\\Next-Level-Practise-1\\logs\\winston\\success\\UMS-2023-06-09-12.log",
            "hash": "908fc339b2a4fd2d230c3d157488fd7954029081cacc5171b949e8e8cec3bb0d"
        },
        {
            "date": 1686303444275,
            "name": "H:\\All project\\Programming Hero\\Next-Level-Practise-1\\logs\\winston\\success\\UMS-2023-06-09-15.log",
            "hash": "ed25735758a2edbdc923b1f739a6ad58713a7d5c08b90781876b6e8c5a11a21a"
        },
        {
            "date": 1686310733395,
            "name": "H:\\All project\\Programming Hero\\Next-Level-Practise-1\\logs\\winston\\success\\UMS-2023-06-09-17.log",
            "hash": "aa29fa48cf49af7ed7c3573385b8f8ae370ef5c2ec15c09ca7bcc036045054ba"
        },
        {
            "date": 1686312009592,
            "name": "H:\\All project\\Programming Hero\\Next-Level-Practise-1\\logs\\winston\\success\\UMS-2023-06-09-18.log",
            "hash": "46e978a53682c8de0d1ceb8e0a5fb37b3ddc66bf62153d425aad50869ea109bd"
        }
    ],
    "hashType": "sha256"
}